funcx_common/__init__.py
funcx_common/funcx_flake8.py
funcx_common/py.typed
funcx_common/redis_endpoint_lock.py
funcx_common/redis_task.py
funcx_common/sdk_version_sharing.py
funcx_common/testing.py
funcx_common/messagepack/__init__.py
funcx_common/messagepack/exceptions.py
funcx_common/messagepack/packer.py
funcx_common/messagepack/protocol.py
funcx_common/messagepack/message_types/__init__.py
funcx_common/messagepack/message_types/base.py
funcx_common/messagepack/message_types/container.py
funcx_common/messagepack/message_types/ep_status_report.py
funcx_common/messagepack/message_types/manager_status_report.py
funcx_common/messagepack/message_types/result.py
funcx_common/messagepack/message_types/task.py
funcx_common/messagepack/message_types/task_cancel.py
funcx_common/messagepack/message_types/task_transition.py
funcx_common/messagepack/protocol_versions/__init__.py
funcx_common/messagepack/protocol_versions/proto1.py
funcx_common/redis/__init__.py
funcx_common/redis/connection.py
funcx_common/redis/fields.py
funcx_common/redis/pubsub.py
funcx_common/redis/serde.py
funcx_common/redis/task_queue.py
funcx_common/task_storage/__init__.py
funcx_common/task_storage/base.py
funcx_common/task_storage/default_storage.py
funcx_common/task_storage/redis.py
funcx_common/task_storage/s3.py
funcx_common/tasks/__init__.py
funcx_common/tasks/constants.py
funcx_common/tasks/protocol.py
funcx_common-0.0.25.dist-info/METADATA
funcx_common-0.0.25.dist-info/WHEEL
funcx_common-0.0.25.dist-info/top_level.txt
funcx_common-0.0.25.dist-info/RECORD
